ipfspod/__init__.py
ipfspod/__main__.py
ipfspod/feed_template.xml.jinja
ipfspod/icon.png
ipfspod/picnic.min.css.gz
ipfspod/test_main.py
ipfspod-0.1.1.dist-info/LICENSE
ipfspod-0.1.1.dist-info/WHEEL
ipfspod-0.1.1.dist-info/METADATA
ipfspod-0.1.1.dist-info/RECORD
