Metadata-Version: 2.1
Name: ipfspod
Version: 0.1.1
Summary: Publish audio, video, or text podcasts on IPFS without centralized hosting 
Home-page: https://github.com/SeanTater/ipfspod
License: UNKNOWN
Author: Sean Gallagher
Author-email: stgallag@gmail.com
Requires-Dist: Jinja2 >= 2.11.2
Requires-Dist: filetype
Requires-Dist: importlib_resources
